{
  "parent": "minecraft:recipes/root",
  "criteria": {
    "hasCrimsonMossyDarkOakWood": {
      "conditions": {
        "items": [
          {
            "items": "#nemos_mossy_blocks:crimson_mossy_dark_oak_wood"
          }
        ]
      },
      "trigger": "minecraft:inventory_changed"
    },
    "has_the_recipe": {
      "conditions": {
        "recipe": "nemos_woodcutter:crimson_mossy_dark_oak_fence_gate_from_crimson_mossy_dark_oak_wood_woodcutting"
      },
      "trigger": "minecraft:recipe_unlocked"
    }
  },
  "requirements": [
    [
      "has_the_recipe",
      "hasCrimsonMossyDarkOakWood"
    ]
  ],
  "rewards": {
    "recipes": [
      "nemos_woodcutter:crimson_mossy_dark_oak_fence_gate_from_crimson_mossy_dark_oak_wood_woodcutting"
    ]
  }
}